basket_case/__init__.py
basket_case/__meta__.py
basket_case/test_main.py
basket_case-0.1.1.dist-info/LICENSE
basket_case-0.1.1.dist-info/METADATA
basket_case-0.1.1.dist-info/WHEEL
basket_case-0.1.1.dist-info/top_level.txt
basket_case-0.1.1.dist-info/RECORD
